pycardkit/__init__.py
pycardkit/card.py
pycardkit/card_context.py
pycardkit/deck.py
pycardkit-1.3.dist-info/METADATA
pycardkit-1.3.dist-info/WHEEL
pycardkit-1.3.dist-info/top_level.txt
pycardkit-1.3.dist-info/RECORD
