Metadata-Version: 2.1
Name: pycardkit
Version: 1.3
